README.rst
setup.py
Thestral/Thestral.py
Thestral/__init__.py
Thestral.egg-info/PKG-INFO
Thestral.egg-info/SOURCES.txt
Thestral.egg-info/dependency_links.txt
Thestral.egg-info/requires.txt
Thestral.egg-info/top_level.txt
Thestral/MAC_Cluster_Ensembles/Cluster_Ensembles.py
Thestral/MAC_Cluster_Ensembles/__init__.py
Thestral/SIMLR/SIMLR_helper.py
Thestral/SIMLR/__init__.py
Thestral/SIMLR/core.py