Metadata-Version: 1.2
Name: Thestral
Version: 0.5.0
Summary: A simple single cell RNA-seq analysis package
Home-page: https://github.com/Fang-Kevin/Thestral
Author: Fang Jingwen
Author-email: fjingwen@mail.ustc.edu.cn
License: MIT
Keywords: Singel-cell RNA-seq
Platform: UNKNOWN
Classifier: Development Status :: 2 - Pre-Alpha
Classifier: Intended Audience :: Science/Research
Classifier: Topic :: Software Development :: Build Tools
Classifier: License :: OSI Approved :: MIT License
Classifier: Programming Language :: Python :: 2.7
Requires-Python: >=2.6, !=3.*.*,<4
